vid_mng-1.0.0.dist-info/METADATA
vid_mng-1.0.0.dist-info/WHEEL
vid_mng-1.0.0.dist-info/entry_points.txt
vid_mng/__init__.py
vid_mng/vid_mng.py
vid_mng-1.0.0.dist-info/RECORD
